flask_s3.py
Flask_S3-0.3.3.dist-info/DESCRIPTION.rst
Flask_S3-0.3.3.dist-info/METADATA
Flask_S3-0.3.3.dist-info/RECORD
Flask_S3-0.3.3.dist-info/WHEEL
Flask_S3-0.3.3.dist-info/metadata.json
Flask_S3-0.3.3.dist-info/top_level.txt
