Metadata-Version: 1.1
Name: Flask-S3
Version: 0.3.3
Summary: Seamlessly serve the static files of your Flask app from Amazon S3
Home-page: http://github.com/e-dard/flask-s3
Author: Edward Robinson
Author-email: hi@edd.io
License: WTFPL
Platform: any
Classifier: Environment :: Web Environment
Classifier: Intended Audience :: Developers
Classifier: License :: Other/Proprietary License
Classifier: Operating System :: OS Independent
Classifier: Programming Language :: Python
Classifier: Topic :: Internet :: WWW/HTTP :: Dynamic Content
Classifier: Topic :: Software Development :: Libraries :: Python Modules
